museparation/__init__.py
museparation/scripts/__init__.py
museparation/scripts/get_musdb.py
museparation/util/__init__.py
museparation/util/create_hdf.py
museparation/util/load_audio.py
museparation/util/load_dataset.py
museparation/util/random_amplify.py
museparation/util/shuffle_train_set.py
museparation/util/split_validation.py
museparation/util/write_wav.py
museparation/waveunet/__init__.py
museparation/waveunet/cog_predict.py
museparation/waveunet/predict.py
museparation/waveunet/test.py
museparation/waveunet/train.py
museparation/waveunet/utils.py
museparation/waveunet/data/__init__.py
museparation/waveunet/data/dataset.py
museparation/waveunet/data/musdb.py
museparation/waveunet/data/utils.py
museparation/waveunet/model/__init__.py
museparation/waveunet/model/conv.py
museparation/waveunet/model/crop.py
museparation/waveunet/model/resample.py
museparation/waveunet/model/utils.py
museparation/waveunet/model/waveunet.py
museparation/waveunet2/__init__.py
museparation/waveunet2/dataloader.py
Museparation-0.0.1a19.dist-info/LICENSE
Museparation-0.0.1a19.dist-info/METADATA
Museparation-0.0.1a19.dist-info/WHEEL
Museparation-0.0.1a19.dist-info/top_level.txt
Museparation-0.0.1a19.dist-info/RECORD
