Metadata-Version: 2.1
Name: Museparation
Version: 0.0.1a19
Summary: Simple scripts for music separation tasks
Home-page: https://github.com/B-lanc/Museparation
Author: Jerry Hatulusan Tobing
Author-email: jerry.tobing@binus.ac.id
Project-URL: Bug Tracker, https://github.com/B-lanc/Museparation/issues
Classifier: Development Status :: 1 - Planning
Classifier: Topic :: Multimedia :: Sound/Audio :: Analysis
Classifier: Programming Language :: Python :: 3
Classifier: License :: OSI Approved :: MIT License
Classifier: Operating System :: OS Independent
License-File: LICENSE
